LICENSE
MANIFEST.in
README.rst
setup.cfg
setup.py
versioneer.py
tests/__init__.py
tests/test_general.py
tpDcc/__init__.py
tpDcc/libs/__init__.py
tpDcc/libs/unittests/__init__.py
tpDcc/libs/unittests/__logging__.ini
tpDcc/libs/unittests/__version__.py
tpDcc/libs/unittests/_version.py
tpDcc/libs/unittests/loader.py
tpDcc/libs/unittests/core/__init__.py
tpDcc/libs/unittests/core/consts.py
tpDcc/libs/unittests/core/result.py
tpDcc/libs/unittests/core/settings.py
tpDcc/libs/unittests/core/unittestcase.py
tpDcc/libs/unittests/core/unittestlib.py
tpDcc/libs/unittests/dccs/__init__.py
tpDcc/libs/unittests/dccs/maya/__init__.py
tpDcc/libs/unittests/dccs/maya/result.py
tpDcc/libs/unittests/dccs/maya/scripteditor.py
tpDcc/libs/unittests/dccs/maya/settings.py
tpDcc/libs/unittests/dccs/maya/unittestcase.py
tpDcc/libs/unittests/dccs/maya/unittestlib.py
tpDcc_libs_unittests.egg-info/PKG-INFO
tpDcc_libs_unittests.egg-info/SOURCES.txt
tpDcc_libs_unittests.egg-info/dependency_links.txt
tpDcc_libs_unittests.egg-info/not-zip-safe
tpDcc_libs_unittests.egg-info/requires.txt
tpDcc_libs_unittests.egg-info/top_level.txt